{
    "x": ["misc"], 
    "a": ["address", "user_address"], 
    "dob": ["dob", "dateofbirth", "user_birthday", "birthday", "birthdate", "DATE_OF_BIRTH"], 
    "e": ["email", "mail", "usr_email", "email_address", "user_email", "emailaddress", "user_email"], 
    "fn": ["first_name", "first", "firstname", "fname"], 
    "h": ["hash", "members_pass_hash", "pass_hash"], 
    "n": ["members_display_name", "display_name", "user_name", "real_name", "name", "display_name"], 
    "u": ["members_l_username", "members_username", "username", "user_login"], 
    "s": ["members_pass_salt", "pass_salt", "salt", "secret"], 
    "i": ["ip", "ipaddress", "ip_address", "ip", "ipaddress", "sourceip", "source_ip", "reg_ip", "regip", "lastip", "last_ip"], 
    "t": ["mobile", "phone", "phone", "PHONE_NUM", "phone_num"], 
    "p": ["pass", "password", "token", "usr_pass", "user_password", "userpassword", "user_pass"], 
    "ln": ["last_name", "last", "lastname", "lname", "lastname"], 
    "a1": ["street", "street_address", "streetaddress", "RESIDENTIAL_ADDRESS"], 
    "a2": ["city", "RESIDENTIAL_CITY"], 
    "a3": ["state", "RESIDENTIAL_STATE"], 
    "a4": ["zip", "zip_code", "zipcode", "RESIDENTIAL_ZIP_CODE", "postalcode", "postal_code"], 
    "a5": ["country"], 
    "o": ["jabber", "xmpp"], 
    "de": ["device"], 
    "did": ["deviceid", "uuid"],
    "fbid": ["facebookid", "fbid", "fbuserid", "facebook_id", "fb_id", "facebook", "face_book", "face_book_id"],
    "fb": ["facebookuser", "fbname", "facebook_url", "face_book_url", "fburl", "fb_url"]
}
